{"pws": {"id": 1053026, "name": "Berkshire Pizzeria", "class": "NC", "town": "Charlemont", "winter": 25, "summer": 25, "connections": 1, "mone": "72 Main Street", "mtwo": "", "mtown": "Charlemont", "mstate": "MA", "mzip": "01339"}, "documents": [{"type": "cert", "ftype": "pdf", "fsize": "92.389KB", "year": "2024", "revoked": false, "url": "https://drive.google.com/file/d/1gGryErrxLU_Tm6yR7aSOX5n3qnOF8kap/view?usp=drivesdk"}, {"type": "ccr", "ftype": "pdf", "fsize": "118.831KB", "year": "2024", "revoked": false, "url": "https://drive.google.com/file/d/1k8dVhgys33phS8nGm3mFq4JcOMZ3-l8m/view?usp=drivesdk"}, {"type": "cms", "ftype": "pdf", "fsize": "331.379KB", "year": "2023-2025", "revoked": false, "url": "https://drive.google.com/file/d/1kNlAjd4rdCM74PCthxPKS0_I_ORL0Swa/view?usp=drivesdk"}]}