{"pws": {"id": 1058000, "name": "Cheshire Water Dept", "class": "COM", "town": "Cheshire", "winter": 1407, "summer": 1407, "connections": 571, "mone": "80 Church St", "mtwo": "", "mtown": "Cheshire", "mstate": "MA", "mzip": "01225", "status": "ACTIVE"}, "documents": [{"type": "asr", "files": []}, {"type": "ccr", "files": [{"ftype": "pdf", "fsize": "202.177KB", "year": "2012", "revoked": false, "url": "https://drive.google.com/file/d/1LDMaXPxi5dURObgcdOUUydkis-BjcvoL/view?usp=drivesdk"}, {"ftype": "pdf", "fsize": "212.557KB", "year": "2013", "revoked": false, "url": "https://drive.google.com/file/d/1izuJ4EFaEadGQWk04C1U_xUwCvSsenfc/view?usp=drivesdk"}, {"ftype": "pdf", "fsize": "218.905KB", "year": "2014", "revoked": false, "url": "https://drive.google.com/file/d/1jsyvIXm0PpmP-zdq75jqO588h-K97Wdx/view?usp=drivesdk"}, {"ftype": "pdf", "fsize": "537.396KB", "year": "2015", "revoked": false, "url": "https://drive.google.com/file/d/12Lxepu4unWIS3awomwt53weeewhFqgsb/view?usp=drivesdk"}, {"ftype": "pdf", "fsize": "1.058061MB", "year": "2016", "revoked": false, "url": "https://drive.google.com/file/d/1uWjj2G6aoYL4_qgtTJbkp3nr8IocYeow/view?usp=drivesdk"}, {"ftype": "pdf", "fsize": "695.87KB", "year": "2017", "revoked": false, "url": "https://drive.google.com/file/d/1JrSr4iDpBLlBUrbOmt9qG4ve-SGx_g2R/view?usp=drivesdk"}, {"ftype": "pdf", "fsize": "578.354KB", "year": "2018", "revoked": false, "url": "https://drive.google.com/file/d/1eLJ9qqp5mIIAeWgOQwUPIUeZH134xg-2/view?usp=drivesdk"}, {"ftype": "pdf", "fsize": "898.62KB", "year": "2019", "revoked": false, "url": "https://drive.google.com/file/d/1CLnrBqF8vXjXhFp22S5geLqvazA3QG7K/view?usp=drivesdk"}, {"ftype": "pdf", "fsize": "422.053KB", "year": "2020", "revoked": false, "url": "https://drive.google.com/file/d/1-nwPOQXt-G5KRBiqpiMsPxnLXjuyqOQb/view?usp=drivesdk"}, {"ftype": "pdf", "fsize": "485.539KB", "year": "2021", "revoked": false, "url": "https://drive.google.com/file/d/1bzbJbMJOEQWxyF2-7XUexKxVqad8dQMW/view?usp=drivesdk"}, {"ftype": "pdf", "fsize": "247.337KB", "year": "2022", "revoked": false, "url": "https://drive.google.com/file/d/1wi-cdSxrbtTxHwZIDzJ7Q8IExX8oZJYA/view?usp=drivesdk"}, {"ftype": "pdf", "fsize": "313.201KB", "year": "2023", "revoked": false, "url": "https://drive.google.com/file/d/1L_Yp6v7J5AwSExtO2vvUtrnKuUOABiiK/view?usp=drivesdk"}, {"ftype": "pdf", "fsize": "272.123KB", "year": "2024", "revoked": false, "url": "https://drive.google.com/file/d/1FjwLBDwj53aySJVgvs7lzuHi-8Em740S/view?usp=drivesdk"}, {"ftype": "pdf", "fsize": "504.118KB", "year": "2025", "revoked": false, "url": "https://drive.google.com/file/d/14w-RPjwVX1PMmrxq7LBTGY7qi4CfuCUG/view?usp=drivesdk"}]}, {"type": "cert", "files": [{"ftype": "pdf", "fsize": "107.129KB", "year": "2015", "revoked": false, "url": "https://drive.google.com/file/d/1roQGI3LDIPwMX94emUhYB84NPWWBfTPu/view?usp=drivesdk"}, {"ftype": "pdf", "fsize": "106.864KB", "year": "2016", "revoked": false, "url": "https://drive.google.com/file/d/1hOtsvdjRKlG4_K6XWj77FKl78WuBM0fs/view?usp=drivesdk"}, {"ftype": "pdf", "fsize": "95.077KB", "year": "2017", "revoked": false, "url": "https://drive.google.com/file/d/1jdPeJbIxNba63ikXzK0kWVKxUiV0TiCZ/view?usp=drivesdk"}, {"ftype": "pdf", "fsize": "95.878KB", "year": "2018", "revoked": false, "url": "https://drive.google.com/file/d/1MR-mhB_flONdasniGcOYgAJ_6NiIp-6l/view?usp=drivesdk"}, {"ftype": "pdf", "fsize": "95.67KB", "year": "2019", "revoked": false, "url": "https://drive.google.com/file/d/1FT2-ixWcyb-tBgHEhSVcXYQbAdrn9Xwk/view?usp=drivesdk"}, {"ftype": "pdf", "fsize": "95.337KB", "year": "2020", "revoked": false, "url": "https://drive.google.com/file/d/1hba5oRvh1OCA3n-WW8qJFMp06guZB1qI/view?usp=drivesdk"}, {"ftype": "pdf", "fsize": "90.231KB", "year": "2021", "revoked": false, "url": "https://drive.google.com/file/d/1RMZ6mVf4pHga-pfOqJm3DuthBv8_Qb9N/view?usp=drivesdk"}, {"ftype": "pdf", "fsize": "89.741KB", "year": "2022", "revoked": false, "url": "https://drive.google.com/file/d/1E8bVXsQ8pcw8BNqiA-7TIygDzzYaZ3Ft/view?usp=drivesdk"}, {"ftype": "pdf", "fsize": "88.939KB", "year": "2023", "revoked": false, "url": "https://drive.google.com/file/d/13wTqkcxntbK-9xH3c9ZpqB-7DJmyL4r1/view?usp=drivesdk"}, {"ftype": "pdf", "fsize": "90.913KB", "year": "2024", "revoked": false, "url": "https://drive.google.com/file/d/1SGjIdQri49aXY5NJJuuv-O898OLhv3Lm/view?usp=drivesdk"}, {"ftype": "pdf", "fsize": "90.955KB", "year": "2025", "revoked": false, "url": "https://drive.google.com/file/d/18KeH6Gx4lmVaoL99Yt-jDQj4C5iehbIc/view?usp=drivesdk"}]}, {"type": "wqr", "files": []}, {"type": "cms", "files": [{"ftype": "pdf", "fsize": "346.0KB", "year": "2023-2025", "revoked": false, "url": "https://drive.google.com/file/d/1PWVRrnrDLoWKx5_9BkIYajpCrztH8Cu-/view?usp=drivesdk"}, {"ftype": "pdf", "fsize": "116.183KB", "year": "2026-2028", "revoked": false, "url": "https://drive.google.com/file/d/1VQXJ4CKVBrUmWzBayLcWy61K6LBjGfKV/view?usp=drivesdk"}]}, {"type": "lcr", "files": [{"ftype": "pdf", "fsize": "252.303KB", "year": 2023, "revoked": false, "url": "https://drive.google.com/file/d/1Li5uGy1dRCFwFRxA_710ZqIlqL6s-aee/view?usp=drivesdk"}]}, {"type": "sli", "files": [{"ftype": "pdf", "fsize": "92.956KB", "year": 2025, "revoked": false, "url": "https://drive.google.com/file/d/1yAMSYKgFq6uTGfXdZw75ToEdiqshAsYc/view?usp=drivesdk"}]}]}