{"pws": {"id": 1068005, "name": "Conway Inn", "class": "NC", "town": "Conway", "winter": 30, "summer": 30, "connections": 1, "mone": "P.O. Box 49", "mtwo": "", "mtown": "Conway", "mstate": "MA", "mzip": "01341"}, "documents": [{"type": "cert", "ftype": "pdf", "fsize": "91.373KB", "year": "2025", "revoked": false, "url": "https://drive.google.com/file/d/15wdM9rR8k2LReMZG39zD06b1Q0Ev_JIZ/view?usp=drivesdk"}, {"type": "ccr", "ftype": "pdf", "fsize": "194.406KB", "year": "2025", "revoked": false}, {"type": "cms", "ftype": "pdf", "fsize": "333.521KB", "year": "2023-2025", "revoked": false, "url": "https://drive.google.com/file/d/1d2prnT48hRKUYT0zQ3YOpkgDscofWt8l/view?usp=drivesdk"}, {"type": "cms", "ftype": "pdf", "fsize": "345.542KB", "year": "2026-2028", "revoked": false, "url": "https://drive.google.com/file/d/1lrYbuLd9M__ZBVdRJhv2fEzQKFoYHfz9/view?usp=drivesdk"}]}