{"pws": {"id": 1111029, "name": "Pizza Palace", "class": "NC", "town": "Granby", "winter": 25, "summer": 25, "connections": 1, "mone": "20 Easthampton Road", "mtwo": "H-5", "mtown": "Holyoke", "mstate": "MA", "mzip": "01040", "status": "ACTIVE"}, "documents": [{"type": "asr", "files": [{"ftype": "pdf", "fsize": "1.1295419999999998MB", "year": "2024", "revoked": false, "url": "https://drive.google.com/file/d/1fjnFFcO28WyBv_TZV-9ktKMYe2usLhRj/view?usp=drivesdk"}]}, {"type": "ccr", "files": []}, {"type": "cert", "files": [{"ftype": "pdf", "fsize": "106.938KB", "year": "2015", "revoked": false, "url": "https://drive.google.com/file/d/1rF24cK1UQusrhlHr2GjRUKXu3iRisTVt/view?usp=drivesdk"}, {"ftype": "pdf", "fsize": "106.665KB", "year": "2016", "revoked": false, "url": "https://drive.google.com/file/d/1XwPZvu6be2e8RF6y7Kmpzz96FnaOTLjs/view?usp=drivesdk"}, {"ftype": "pdf", "fsize": "94.883KB", "year": "2017", "revoked": false, "url": "https://drive.google.com/file/d/1J6jCxUsjRRtgCyQVDOiPMvbInKLRqlZO/view?usp=drivesdk"}, {"ftype": "pdf", "fsize": "95.575KB", "year": "2018", "revoked": false, "url": "https://drive.google.com/file/d/18i-Jq08uhPdg2ZatGYgsV8Lw1IWT99bG/view?usp=drivesdk"}, {"ftype": "pdf", "fsize": "95.478KB", "year": "2019", "revoked": false, "url": "https://drive.google.com/file/d/1655nQNDdrUDIaWKknYDV4uly889z9Syq/view?usp=drivesdk"}, {"ftype": "pdf", "fsize": "95.145KB", "year": "2020", "revoked": false, "url": "https://drive.google.com/file/d/1fwbw2ySoALmaj1Rjzjtq1dHCn9ZHrW0C/view?usp=drivesdk"}, {"ftype": "pdf", "fsize": "90.024KB", "year": "2021", "revoked": false, "url": "https://drive.google.com/file/d/1BfsaJVLdfx79locfziZqAi8LH28sLl2g/view?usp=drivesdk"}, {"ftype": "pdf", "fsize": "89.544KB", "year": "2022", "revoked": false, "url": "https://drive.google.com/file/d/1brOAAmSlrK3tFp8Vf8Mvz-L1vt2lDKIJ/view?usp=drivesdk"}, {"ftype": "pdf", "fsize": "88.728KB", "year": "2023", "revoked": false, "url": "https://drive.google.com/file/d/1QMcZghWABoUoE4WgfT_wsLLY_LQjGFN7/view?usp=drivesdk"}, {"ftype": "pdf", "fsize": "90.7KB", "year": "2024", "revoked": false, "url": "https://drive.google.com/file/d/1xQP7g9OfGHyvyDYRhbYTHJmfzbJ8FknT/view?usp=drivesdk"}, {"ftype": "pdf", "fsize": "90.744KB", "year": "2025", "revoked": false, "url": "https://drive.google.com/file/d/1yscCHF0_47ljj6dwIyXfCX5ScYMD8bC4/view?usp=drivesdk"}, {"ftype": "pdf", "fsize": "60.212KB", "year": "2026", "revoked": false, "url": "https://drive.google.com/file/d/1eqN6sF75bLOcQgjjUYgfBOtB-a-3quIN/view?usp=drivesdk"}]}, {"type": "wqr", "files": [{"ftype": "pdf", "fsize": "229.103KB", "year": "2015", "revoked": false, "url": "https://drive.google.com/file/d/1ZAyIIQafuxBc2rH4afLMqx9SZdx8ORO8/view?usp=drivesdk"}, {"ftype": "pdf", "fsize": "263.309KB", "year": "2016", "revoked": false, "url": "https://drive.google.com/file/d/1oCpCD3WN_os7nKIv7QpV7uGrFunXRtbA/view?usp=drivesdk"}, {"ftype": "pdf", "fsize": "134.54KB", "year": "2017", "revoked": false, "url": "https://drive.google.com/file/d/1rg_gX9nVC0TFpgCqWEy9X99FTIvKx5-6/view?usp=drivesdk"}, {"ftype": "pdf", "fsize": "134.589KB", "year": "2018", "revoked": false, "url": "https://drive.google.com/file/d/1tWLrDwWb46-XZrofxo14sEFK4o9zNhsE/view?usp=drivesdk"}, {"ftype": "pdf", "fsize": "136.343KB", "year": "2019", "revoked": false, "url": "https://drive.google.com/file/d/1xlAsSjSYIhi7E5SNjK-1lxhnd5QYenJ8/view?usp=drivesdk"}, {"ftype": "pdf", "fsize": "116.617KB", "year": "2020", "revoked": false, "url": "https://drive.google.com/file/d/15IqzETjTMQ0dkSz7je0x15nIzxZVRRIh/view?usp=drivesdk"}, {"ftype": "pdf", "fsize": "118.217KB", "year": "2021", "revoked": false, "url": "https://drive.google.com/file/d/1cgV9odiA98ACXBxQGlEqvcZJt-Vehkez/view?usp=drivesdk"}, {"ftype": "pdf", "fsize": "367.163KB", "year": "2022", "revoked": false, "url": "https://drive.google.com/file/d/15i0Lr4wTDbuj0JL8OnqO5Fz7VP0oeQT_/view?usp=drivesdk"}, {"ftype": "pdf", "fsize": "118.34KB", "year": "2023", "revoked": false, "url": "https://drive.google.com/file/d/1pfqv4OpvSTZUlBLj0Zf4ZaZK71MLIlzB/view?usp=drivesdk"}, {"ftype": "pdf", "fsize": "118.096KB", "year": "2024", "revoked": false, "url": "https://drive.google.com/file/d/14DbC0XanXw0rr4gbPT0nUpXq8oWHa1Vf/view?usp=drivesdk"}, {"ftype": "pdf", "fsize": "197.625KB", "year": "2025", "revoked": false, "url": "https://drive.google.com/file/d/17-DSpi1oW-Ca9BB3hEySWangrAPXtjPA/view?usp=drivesdk"}]}, {"type": "cms", "files": [{"ftype": "pdf", "fsize": "343.558KB", "year": "2023-2025", "revoked": false, "url": "https://drive.google.com/file/d/1YSFwjaO0Wg183_1UPjplY5EiHmjWYwDc/view?usp=drivesdk"}, {"ftype": "pdf", "fsize": "352.804KB", "year": "2026-2028", "revoked": false, "url": "https://drive.google.com/file/d/1eSkrl2cdL_vsI0ell2LvgDcLpjg2RxSD/view?usp=drivesdk"}]}, {"type": "lcr", "files": []}, {"type": "sli", "files": []}]}