{"pws": {"id": 1120006, "name": "Thornton Burgess Middle School", "class": "NTNC", "town": "Hampden", "winter": 270, "summer": 30, "connections": 1, "mone": "Hampden/Wilbraham Regional School Distri", "mtwo": "621 Main Street", "mtown": "Wilbraham", "mstate": "MA", "mzip": "01095", "status": "ACTIVE"}, "documents": [{"type": "asr", "files": [{"ftype": "pdf", "fsize": "1.296059MB", "year": "2024", "revoked": false, "url": "https://drive.google.com/file/d/131VoSps__q06kp-kKWjGnI5mxn42ndr7/view?usp=drivesdk"}]}, {"type": "ccr", "files": []}, {"type": "cert", "files": [{"ftype": "pdf", "fsize": "107.744KB", "year": "2015", "revoked": false, "url": "https://drive.google.com/file/d/13PPjUjd81NIDqaXuYsX37McY4OuYTrPU/view?usp=drivesdk"}, {"ftype": "pdf", "fsize": "107.481KB", "year": "2016", "revoked": false, "url": "https://drive.google.com/file/d/15Ze3eM6IGofFvSpA1p5e1sZv4g1y4Iy0/view?usp=drivesdk"}, {"ftype": "pdf", "fsize": "95.686KB", "year": "2017", "revoked": false, "url": "https://drive.google.com/file/d/1o40OFpqZ6jQy3_UC9S67vtdz_cwpPj4d/view?usp=drivesdk"}, {"ftype": "pdf", "fsize": "96.381KB", "year": "2018", "revoked": false, "url": "https://drive.google.com/file/d/1pVxEH3x8cVsCleaXqpJimarDoh9PpiFF/view?usp=drivesdk"}, {"ftype": "pdf", "fsize": "96.277KB", "year": "2019", "revoked": false, "url": "https://drive.google.com/file/d/11yG-KA0P-s-GFpGEqBNCDxn8bWrYgLX5/view?usp=drivesdk"}, {"ftype": "pdf", "fsize": "95.953KB", "year": "2020", "revoked": false, "url": "https://drive.google.com/file/d/1HejZ0S244Tku6ZEL4z-FiHnSqRQ40qAp/view?usp=drivesdk"}, {"ftype": "pdf", "fsize": "90.829KB", "year": "2021", "revoked": false, "url": "https://drive.google.com/file/d/1PmaViXEDpSjlqtaMHfzkih_fUQHH7wkZ/view?usp=drivesdk"}, {"ftype": "pdf", "fsize": "90.338KB", "year": "2022", "revoked": false, "url": "https://drive.google.com/file/d/1ZZaaRineHqY_9g5ymsQJZGHKG0oxRmuv/view?usp=drivesdk"}, {"ftype": "pdf", "fsize": "89.533KB", "year": "2023", "revoked": false, "url": "https://drive.google.com/file/d/1YmfiiBEjHpstmHqGP9dRA6nkfl26-sbJ/view?usp=drivesdk"}, {"ftype": "pdf", "fsize": "91.511KB", "year": "2024", "revoked": false, "url": "https://drive.google.com/file/d/1NpOZOYJqSqzYjm5Pizy4dwF15ljgl758/view?usp=drivesdk"}, {"ftype": "pdf", "fsize": "91.551KB", "year": "2025", "revoked": false, "url": "https://drive.google.com/file/d/1tdUlU-jNgGqD9RNhKniHQ9n9lkwo-01i/view?usp=drivesdk"}, {"ftype": "pdf", "fsize": "60.423KB", "year": "2026", "revoked": false, "url": "https://drive.google.com/file/d/1Jaq_RJHkxWmlNXQFN1c813r_mTlSJ384/view?usp=drivesdk"}]}, {"type": "wqr", "files": [{"ftype": "pdf", "fsize": "152.865KB", "year": "2015", "revoked": false, "url": "https://drive.google.com/file/d/1QoucNhUAU5k1wxm0KOMz2_VYd6-1nW7t/view?usp=drivesdk"}, {"ftype": "pdf", "fsize": "149.104KB", "year": "2016", "revoked": false, "url": "https://drive.google.com/file/d/1fAw35YSaUr1yzGArD6rBoMDNPbq2Jy9S/view?usp=drivesdk"}, {"ftype": "pdf", "fsize": "147.956KB", "year": "2017", "revoked": false, "url": "https://drive.google.com/file/d/1DT4N-lNV6r4OL3TyxCamtOE0zWIwsgKQ/view?usp=drivesdk"}, {"ftype": "pdf", "fsize": "281.203KB", "year": "2018", "revoked": false, "url": "https://drive.google.com/file/d/1yNFwKgG-F3qNBX_aHB0WUaNqu3Hukawo/view?usp=drivesdk"}, {"ftype": "pdf", "fsize": "204.648KB", "year": "2019", "revoked": false, "url": "https://drive.google.com/file/d/16KLvixYPMzH8mQGis1DiEO3nQpT53RA_/view?usp=drivesdk"}, {"ftype": "pdf", "fsize": "229.329KB", "year": "2020", "revoked": false, "url": "https://drive.google.com/file/d/1ioDFQeVX2O78oXk-uyHBLUWiHykbS1Qe/view?usp=drivesdk"}, {"ftype": "pdf", "fsize": "231.977KB", "year": "2021", "revoked": false, "url": "https://drive.google.com/file/d/1KITLfC4Sy6X0KUbW__aubizStq9WAYq-/view?usp=drivesdk"}, {"ftype": "pdf", "fsize": "374.751KB", "year": "2022", "revoked": false, "url": "https://drive.google.com/file/d/1y4xjr9PYA5jBEpginvN3E2bALAzJM5Sl/view?usp=drivesdk"}, {"ftype": "pdf", "fsize": "374.703KB", "year": "2023", "revoked": false, "url": "https://drive.google.com/file/d/1PgZtpLgOtfpI2PXjJateu4QwHN9kpDwc/view?usp=drivesdk"}, {"ftype": "pdf", "fsize": "363.575KB", "year": "2024", "revoked": false, "url": "https://drive.google.com/file/d/1x8CeZNdB18LayP1CCmb2AEW8513d0lUx/view?usp=drivesdk"}, {"ftype": "pdf", "fsize": "604.565KB", "year": "2025", "revoked": false, "url": "https://drive.google.com/file/d/1xPpqgbShX2_Wu2LJtROK5n_y4nb7Qa1C/view?usp=drivesdk"}]}, {"type": "cms", "files": [{"ftype": "pdf", "fsize": "374.37KB", "year": "2023-2025", "revoked": false, "url": "https://drive.google.com/file/d/19N_CdrxVfYxSHWLvaqSHrSjkZLDEY3Uw/view?usp=drivesdk"}, {"ftype": "pdf", "fsize": "111.791KB", "year": "2026-2028", "revoked": false, "url": "https://drive.google.com/file/d/14UDPc-vSKGOGQY2msDpdXyIiXwi-VNX2/view?usp=drivesdk"}]}, {"type": "lcr", "files": [{"ftype": "pdf", "fsize": "249.133KB", "year": 2023, "revoked": false, "url": "https://drive.google.com/file/d/18TY4L2ZU9A6aEzhyYRDsUIb9-40n3iPl/view?usp=drivesdk"}]}, {"type": "sli", "files": [{"ftype": "pdf", "fsize": "0.933KB", "year": 2025, "revoked": false, "url": "https://drive.google.com/file/d/1aCo29f1xCyxFph7rV4YAFx9j6sMcpNk7/view?usp=drivesdk"}]}]}