{"pws": {"id": 1121013, "name": "Liberty Plaza", "class": "NC", "town": "Hancock", "winter": 25, "summer": 25, "connections": 1, "mone": "175 Lebanon Mt. Road", "mtwo": "", "mtown": "Hancock", "mstate": "MA", "mzip": "01237", "status": "ACTIVE"}, "documents": [{"type": "asr", "files": []}, {"type": "ccr", "files": []}, {"type": "cert", "files": [{"ftype": "pdf", "fsize": "107.032KB", "year": "2015", "revoked": false, "url": "https://drive.google.com/file/d/1J_k7vxTqZQVDYHUbA3cOZv89jppBeMFI/view?usp=drivesdk"}, {"ftype": "pdf", "fsize": "106.766KB", "year": "2016", "revoked": false, "url": "https://drive.google.com/file/d/1F6CkCwS5pjEVighdp97zlURlv5-bUdjR/view?usp=drivesdk"}, {"ftype": "pdf", "fsize": "94.979KB", "year": "2017", "revoked": false, "url": "https://drive.google.com/file/d/1TmvkHnHe6mpPGj2V4Asw8pD6nNAn-9Ym/view?usp=drivesdk"}, {"ftype": "pdf", "fsize": "95.783KB", "year": "2018", "revoked": false, "url": "https://drive.google.com/file/d/1rEZKht03SD-Sih6mzvWnkUJFU3OSig0T/view?usp=drivesdk"}, {"ftype": "pdf", "fsize": "95.58KB", "year": "2019", "revoked": false, "url": "https://drive.google.com/file/d/1-gd8s4SX8pLRV673Vxmxvy0iJHmKFNW1/view?usp=drivesdk"}, {"ftype": "pdf", "fsize": "95.349KB", "year": "2020", "revoked": false, "url": "https://drive.google.com/file/d/1QLDsGw8-N9PmWUGNIT_gHgQuQY2unaxZ/view?usp=drivesdk"}, {"ftype": "pdf", "fsize": "90.17KB", "year": "2021", "revoked": false, "url": "https://drive.google.com/file/d/1T9jTuquvOy8o_jDH80WFlKJvJiFHlZWU/view?usp=drivesdk"}, {"ftype": "pdf", "fsize": "89.681KB", "year": "2022", "revoked": false, "url": "https://drive.google.com/file/d/1L6nlezXN34OyPi1EXR-dqAd0YqQRcMrG/view?usp=drivesdk"}, {"ftype": "pdf", "fsize": "88.87KB", "year": "2023", "revoked": false, "url": "https://drive.google.com/file/d/1eWuSNKmsYzphzyRX2IEdtqFXcsB8poVm/view?usp=drivesdk"}, {"ftype": "pdf", "fsize": "90.842KB", "year": "2024", "revoked": false, "url": "https://drive.google.com/file/d/1termCRnYNtpGMHw4d7CPSDk9RtCZZGdr/view?usp=drivesdk"}, {"ftype": "pdf", "fsize": "91.435KB", "year": "2025", "revoked": false, "url": "https://drive.google.com/file/d/1zQbKNNJN-QZpQV5gMjKtER4R6kqkDQ1L/view?usp=drivesdk"}, {"ftype": "pdf", "fsize": "60.419KB", "year": "2026", "revoked": false, "url": "https://drive.google.com/file/d/1NJOuK8Jjz6c2sAZWMVZWG08RaZ6aeXAs/view?usp=drivesdk"}]}, {"type": "wqr", "files": [{"ftype": "pdf", "fsize": "117.408KB", "year": "2015", "revoked": false, "url": "https://drive.google.com/file/d/1kHxsgHgVhxAZSZQ5tUnroSzBvacrmQr7/view?usp=drivesdk"}, {"ftype": "pdf", "fsize": "135.193KB", "year": "2016", "revoked": false, "url": "https://drive.google.com/file/d/11MD6nj3dWkhpIzbXsJeUvTuy6gTRHe-8/view?usp=drivesdk"}, {"ftype": "pdf", "fsize": "135.1KB", "year": "2017", "revoked": false, "url": "https://drive.google.com/file/d/1ixSyKd8Yh1oMeMgmRmWbRG6QrSBwsJER/view?usp=drivesdk"}, {"ftype": "pdf", "fsize": "134.96KB", "year": "2018", "revoked": false, "url": "https://drive.google.com/file/d/1B461zwjRLAAhLI-hOArPAsj0j61Zvp_p/view?usp=drivesdk"}, {"ftype": "pdf", "fsize": "136.911KB", "year": "2019", "revoked": false, "url": "https://drive.google.com/file/d/1HAq0ARfEbpMm-Yl4pxQycoTJT_uzve3c/view?usp=drivesdk"}, {"ftype": "pdf", "fsize": "117.336KB", "year": "2020", "revoked": false, "url": "https://drive.google.com/file/d/1raYF2h6TZ13HLRytJMu9eTvOubgJOxGu/view?usp=drivesdk"}, {"ftype": "pdf", "fsize": "225.344KB", "year": "2021", "revoked": false, "url": "https://drive.google.com/file/d/1MJs9X6-I_vp6-y7aFpU6X4Nhxb531wPy/view?usp=drivesdk"}, {"ftype": "pdf", "fsize": "263.765KB", "year": "2022", "revoked": false, "url": "https://drive.google.com/file/d/1LfREy5ww-LlhaiWDUEUoXj0O8LNXLvyM/view?usp=drivesdk"}, {"ftype": "pdf", "fsize": "119.071KB", "year": "2023", "revoked": false, "url": "https://drive.google.com/file/d/1X9Lsn6OBgHmKiR9e1Umg0TUxPMfFh1Yu/view?usp=drivesdk"}, {"ftype": "pdf", "fsize": "118.762KB", "year": "2024", "revoked": false, "url": "https://drive.google.com/file/d/1hbPch8H8t8tKidiC1PYYhZPGEClHjQ9E/view?usp=drivesdk"}, {"ftype": "pdf", "fsize": "196.454KB", "year": "2025", "revoked": false, "url": "https://drive.google.com/file/d/1v7bPaO-e3w_FY0djl4dNWhdwH0VxnrZV/view?usp=drivesdk"}]}, {"type": "cms", "files": [{"ftype": "pdf", "fsize": "329.511KB", "year": "2023-2025", "revoked": false, "url": "https://drive.google.com/file/d/1KLnmWFVEDRCP3nypZjaTyjjM4fysOMuO/view?usp=drivesdk"}, {"ftype": "pdf", "fsize": "345.467KB", "year": "2026-2028", "revoked": false, "url": "https://drive.google.com/file/d/1KfLeECS6RvrUKA_W7hy6wjqVS_v-d8j8/view?usp=drivesdk"}]}, {"type": "lcr", "files": []}, {"type": "sli", "files": []}]}