{"pws": {"id": 1148017, "name": "Pittsfield Mold  Tool", "class": "NC", "town": "Lanesborough", "winter": 25, "summer": 25, "connections": 1, "mone": "840 Cheshire Road, Route 8", "mtwo": "", "mtown": "Lanesborough", "mstate": "MA", "mzip": "01237", "status": "DECLASSIFIED"}, "documents": [{"type": "asr", "files": []}, {"type": "ccr", "files": []}, {"type": "cert", "files": []}, {"type": "wqr", "files": []}, {"type": "cms", "files": []}, {"type": "lcr", "files": []}, {"type": "sli", "files": []}]}