{"documents": [{"revoked": false, "url": "https://drive.google.com/file/d/1SRkIYojSa8xC0eEQD3PrGRiOIcLdUejG/view?usp=drivesdk", "fsize": "95KB", "ftype": "pdf", "year": "2018", "type": "cert"}, {"revoked": false, "url": "https://drive.google.com/file/d/1pPPLf_le7__eimUlXJ3n2FUwMexu6ULz/view?usp=drivesdk", "fsize": "35KB", "ftype": "pdf", "year": "2017-2019", "type": "cms"}, {"revoked": false, "url": "https://drive.google.com/file/d/1_Lvrg9ijGS7bakqM6iAIhL84TSLtgLcN/view?usp=drivesdk", "fsize": "458KB", "ftype": "pdf", "year": "", "type": "lcr"}], "pws": {"town": "North Adams", "summer": 13000, "mone": "10 Main St City Hall", "winter": 13000, "mtwo": "", "mzip": "01247", "id": 1209000, "connections": 4203, "mtown": "North Adams", "class": "COM", "mstate": "MA", "name": "North Adams Water Dept"}}