{"documents": [{"revoked": false, "url": "https://drive.google.com/file/d/1UvV0IeppJBiV9U_YYFfhOUKYlnih0rOh/view?usp=drivesdk", "fsize": "95KB", "ftype": "pdf", "year": "2019", "type": "cert"}, {"revoked": false, "url": "https://drive.google.com/file/d/1XmIKWG2RWrZ9aJACsTRHySweEAgff7fY/view?usp=drivesdk", "fsize": "135KB", "ftype": "pdf", "year": "2018", "type": "ccr"}, {"revoked": false, "url": "https://drive.google.com/file/d/1WRvKOiLrdJ23CwOV2XcdxvOaYI2H9w92/view?usp=drivesdk", "fsize": "7KB", "ftype": "pdf", "year": "2017-2019", "type": "cms"}], "pws": {"town": "Shelburne", "summer": 95, "mone": "Attn   Laura Sandvik", "winter": 75, "mtwo": "386 Colrain Shelburne Road", "mzip": "01370", "id": 1268010, "connections": 2, "mtown": "Shelburne", "class": "NC", "mstate": "MA", "name": "Vipassana Meditation Center"}}