{"pws": {"id": 1309008, "name": "Primo Water @ Wal Mart Super Ctr #2386", "class": "NC", "town": "Ware", "winter": 25, "summer": 25, "connections": 1, "mone": "2615 Temple Heights Drive", "mtwo": "", "mtown": "Oceanside", "mstate": "CA", "mzip": "92056"}, "documents": [{"type": "cert", "ftype": "pdf", "fsize": "92.373KB", "year": "2025", "revoked": false, "url": "https://drive.google.com/file/d/1iYP6aP4sw94lyj53cWD8D-MlugIMYes0/view?usp=drivesdk"}, {"type": "ccr", "ftype": "pdf", "fsize": "196.14KB", "year": "2025", "revoked": false}, {"type": "cms", "ftype": "pdf", "fsize": "337.002KB", "year": "2023-2025", "revoked": false, "url": "https://drive.google.com/file/d/1x8lWSBjoFrQ9AJBBUExeEDkSRD3nybst/view?usp=drivesdk"}, {"type": "cms", "ftype": "pdf", "fsize": "344.178KB", "year": "2026-2028", "revoked": false, "url": "https://drive.google.com/file/d/1ZfNJp8uNkK5FDFo1IIYbYq5VrYagDfPW/view?usp=drivesdk"}]}