{"pws": {"id": 1312012, "name": "Warwick Community School", "class": "NTNC", "town": "Warwick", "winter": 100, "summer": 100, "connections": 1, "mone": "41 Winchester Road", "mtwo": "Attn: Tim Brandl", "mtown": "Warwick", "mstate": "MA", "mzip": "01378"}, "documents": [{"type": "cert", "ftype": "pdf", "fsize": "89.934KB", "year": "2023", "revoked": false, "url": "https://drive.google.com/file/d/1oMlDAlib7lffsyXG_SouCKhXLZCOcNc_/view?usp=drivesdk"}, {"type": "ccr", "ftype": "pdf", "fsize": "376.443KB", "year": "2022", "revoked": false, "url": "https://drive.google.com/file/d/1BI6JkOUMNmv4TuTvE6I0pxEDIH6BjFcB/view?usp=drivesdk"}, {"type": "cms", "ftype": "pdf", "fsize": "347.987KB", "year": "2023-2025", "revoked": false, "url": "https://drive.google.com/file/d/1M-kZCrAqAsDcGOXS5kvnLYf9tTV-tT6J/view?usp=drivesdk"}, {"type": "lcr", "ftype": "pdf", "fsize": "444.615KB", "year": "", "revoked": false, "url": "https://drive.google.com/file/d/1PI_lSdQZ2bfyMFb6FfpjfkCIep4C5Vp3/view?usp=drivesdk"}]}