{"pws": {"id": 1329007, "name": "R E G Enterprises Inc", "class": "NC", "town": "Westfield", "winter": 25, "summer": 25, "connections": 1, "mone": "39 College Highway", "mtwo": "", "mtown": "Southampton", "mstate": "MA", "mzip": "01073"}, "documents": [{"type": "cert", "ftype": "pdf", "fsize": "95.874KB", "year": "2020", "revoked": false, "url": "https://drive.google.com/file/d/1-_AT7655S2bec2DNTzT-gaGrdvvRWq67/view?usp=drivesdk"}, {"type": "ccr", "ftype": "pdf", "fsize": "135.88KB", "year": "2019", "revoked": false, "url": "https://drive.google.com/file/d/1s35KF77DMfLv3cSdNCCo4tBRZrcp5Vjt/view?usp=drivesdk"}, {"type": "cms", "ftype": "pdf", "fsize": "854.844KB", "year": "2020-2022", "revoked": false, "url": "https://drive.google.com/file/d/1HHOAfI0rV2fb6g-EfggboIqxzTqJhG5e/view?usp=drivesdk"}]}