{"pws": {"id": 1339000, "name": "Wilbraham Water Dept (Mwra)", "class": "COM", "town": "Wilbraham", "winter": 8533, "summer": 8533, "connections": 3289, "mone": "240 Springfield St", "mtwo": "", "mtown": "Wilbraham", "mstate": "MA", "mzip": "01095"}, "documents": [{"type": "cert", "ftype": "pdf", "fsize": "91.394KB", "year": "2025", "revoked": false, "url": "https://drive.google.com/file/d/1sBcrXoq7fiuACeVUjvcBteh2jQgzCUQ2/view?usp=drivesdk"}, {"type": "cms", "ftype": "pdf", "fsize": "355.752KB", "year": "2023-2025", "revoked": false, "url": "https://drive.google.com/file/d/1QxOVlOYRu_QdFJtxXMYV2Gd0GtJKi-ns/view?usp=drivesdk"}, {"type": "cms", "ftype": "pdf", "fsize": "336.796KB", "year": "2026-2028", "revoked": false, "url": "https://drive.google.com/file/d/1KcNqtUd5rr2VbCu2yNJf_q2v5a_f3H7H/view?usp=drivesdk"}, {"type": "lcr", "ftype": "pdf", "fsize": "200.972KB", "year": "", "revoked": false, "url": "https://drive.google.com/file/d/1kJeTm6jdBHxrgAhbVLv7uuB5gXctN4wy/view?usp=drivesdk"}, {"type": "sli", "ftype": "csv", "fsize": "458.067KB", "year": "2024", "revoked": false, "url": "https://drive.google.com/file/d/1IgBDdOeq2qTbJkBMAh6QS46TdXIPu_6F/view?usp=drivesdk"}]}