{"pws": {"id": 2037034, "name": "Cisco Systems Inc. Site Ii", "class": "NTNC", "town": "Boxborough", "winter": 1100, "summer": 1100, "connections": 4, "mone": "Attn:  Don Bird", "mtwo": "1414 Massachusetts Ave", "mtown": "Boxborough", "mstate": "MA", "mzip": "01719"}, "documents": [{"type": "cert", "ftype": "pdf", "fsize": "95.879KB", "year": "2020", "revoked": false, "url": "https://drive.google.com/file/d/1srRBdbvchSFLTHa3f94Mbp3x2IgFAUjw/view?usp=drivesdk"}, {"type": "ccr", "ftype": "pdf", "fsize": "206.871KB", "year": "2019", "revoked": false, "url": "https://drive.google.com/file/d/1mWIGrDHNF3koN3KMvtDYFMQ4dDEpEHGK/view?usp=drivesdk"}, {"type": "cms", "ftype": "pdf", "fsize": "341.282KB", "year": "2020-2022", "revoked": false, "url": "https://drive.google.com/file/d/11oOOeYnmTjHe7H7XRgmeqmzLQg8WLoXG/view?usp=drivesdk"}, {"type": "lcr", "ftype": "pdf", "fsize": "368.739KB", "year": "", "revoked": false, "url": "https://drive.google.com/file/d/1wb4HOB0oej-dT3-rPR7BMQ6Kjnit-tf2/view?usp=drivesdk"}]}