{"pws": {"id": 2280008, "name": "Dcr Spencer State Forest", "class": "NC", "town": "Spencer", "winter": 0, "summer": 100, "connections": 1, "mone": "P.O. Box 484", "mtwo": "40 Cold Storage Drive", "mtown": "Amherst", "mstate": "MA", "mzip": "01004"}, "documents": [{"type": "cert", "ftype": "pdf", "fsize": "89.294KB", "year": "2022", "revoked": false, "url": "https://drive.google.com/file/d/1aQqClf1VOXZDQb2sqTSCI8EIw3cNoaZy/view?usp=drivesdk"}, {"type": "ccr", "ftype": "pdf", "fsize": "117.167KB", "year": "2022", "revoked": false, "url": "https://drive.google.com/file/d/1Vq9WiWznnE3GeBAi9chjrygtExCh1HBp/view?usp=drivesdk"}, {"type": "cms", "ftype": "pdf", "fsize": "18.49KB", "year": "2020-2022", "revoked": false, "url": "https://drive.google.com/file/d/1DmCnD1Uutub63SCYLEmimG2QNDNHUzzc/view?usp=drivesdk"}, {"type": "cms", "ftype": "pdf", "fsize": "334.036KB", "year": "2023-2025", "revoked": false, "url": "https://drive.google.com/file/d/18RAge28hw53Nbu4KTeRPrgCBRHzO1Emz/view?usp=drivesdk"}]}