{"pws": {"id": 2286019, "name": "Stow Industrial (Flb Incorporated)", "class": "NTNC", "town": "Stow", "winter": 25, "summer": 25, "connections": 4, "mone": "6 Wayne Road", "mtwo": "", "mtown": "Westford", "mstate": "MA", "mzip": "01886", "status": "ACTIVE"}, "documents": [{"type": "asr", "files": []}, {"type": "ccr", "files": []}, {"type": "cert", "files": [{"ftype": "pdf", "fsize": "107.589KB", "year": "2015", "revoked": false, "url": "https://drive.google.com/file/d/1S776PF-unDevNwFNOA6s-7JGbRczFj7U/view?usp=drivesdk"}, {"ftype": "pdf", "fsize": "107.314KB", "year": "2016", "revoked": false, "url": "https://drive.google.com/file/d/1hQxcK1E5-NU1T6A3dsszEuFCvYDWOEg8/view?usp=drivesdk"}, {"ftype": "pdf", "fsize": "95.528KB", "year": "2017", "revoked": false, "url": "https://drive.google.com/file/d/1RBrXtSmXWYbiK4GdST3zQoOUMRgjtHgI/view?usp=drivesdk"}, {"ftype": "pdf", "fsize": "96.225KB", "year": "2018", "revoked": false, "url": "https://drive.google.com/file/d/1wcRx7eo4evkHDtZLrq41aJ8wvX1eYjs_/view?usp=drivesdk"}, {"ftype": "pdf", "fsize": "96.24KB", "year": "2019", "revoked": false, "url": "https://drive.google.com/file/d/1A5g_iZ9cIaWAsYfjkDRZ2r6HvY5CuZoC/view?usp=drivesdk"}, {"ftype": "pdf", "fsize": "96.416KB", "year": "2020", "revoked": false, "url": "https://drive.google.com/file/d/1c6ucTzm6Cm5YZ-a9V2b3AlVz8NsSGDy7/view?usp=drivesdk"}, {"ftype": "pdf", "fsize": "91.216KB", "year": "2021", "revoked": false, "url": "https://drive.google.com/file/d/13HMxKxYbxpRTa5qzTxjllPZF4RKg09ll/view?usp=drivesdk"}, {"ftype": "pdf", "fsize": "90.227KB", "year": "2022", "revoked": false, "url": "https://drive.google.com/file/d/1lwlCNqmF25ewWrORMDBaHFlYUeFQLv61/view?usp=drivesdk"}, {"ftype": "pdf", "fsize": "89.919KB", "year": "2023", "revoked": false, "url": "https://drive.google.com/file/d/1ExPCjdOj8_yzTB7SHFllj0s5yB9Ygg3L/view?usp=drivesdk"}, {"ftype": "pdf", "fsize": "91.893KB", "year": "2024", "revoked": false, "url": "https://drive.google.com/file/d/1Dw4QGp3ToCXnsUwwUdK5vrC09NAxpXhr/view?usp=drivesdk"}, {"ftype": "pdf", "fsize": "91.931KB", "year": "2025", "revoked": false, "url": "https://drive.google.com/file/d/1cjSXHZt15kj8bYI35z4IePZN5HYdoLf8/view?usp=drivesdk"}, {"ftype": "pdf", "fsize": "61.234KB", "year": "2026", "revoked": false, "url": "https://drive.google.com/file/d/152n5N6DCK2e92q_Q6hKWSzZWt1gNYkxb/view?usp=drivesdk"}]}, {"type": "wqr", "files": [{"ftype": "pdf", "fsize": "99.81KB", "year": "2015", "revoked": false, "url": "https://drive.google.com/file/d/1cDoW-pXJB7JUkVmuf9j_o9BgcvpT6RAc/view?usp=drivesdk"}, {"ftype": "pdf", "fsize": "232.281KB", "year": "2016", "revoked": false, "url": "https://drive.google.com/file/d/1mczvKpF8omR8BwMeVfHkO-36E_SDXBXW/view?usp=drivesdk"}, {"ftype": "pdf", "fsize": "149.601KB", "year": "2017", "revoked": false, "url": "https://drive.google.com/file/d/1IynkKFPvcQfmYj2XdyG15wgnZw3rEBie/view?usp=drivesdk"}, {"ftype": "pdf", "fsize": "206.539KB", "year": "2018", "revoked": false, "url": "https://drive.google.com/file/d/1a14IkcNJoMaRZW-g3X3kQ0FOo3tXU4Jd/view?usp=drivesdk"}, {"ftype": "pdf", "fsize": "291.258KB", "year": "2019", "revoked": false, "url": "https://drive.google.com/file/d/1AJS0gQV2RpqMxfrzbD_sIefGrtm9WJbY/view?usp=drivesdk"}, {"ftype": "pdf", "fsize": "233.111KB", "year": "2020", "revoked": false, "url": "https://drive.google.com/file/d/1R2O1iwbQHYgiIiehz23uF2PwXE_2Z23e/view?usp=drivesdk"}, {"ftype": "pdf", "fsize": "233.581KB", "year": "2021", "revoked": false, "url": "https://drive.google.com/file/d/1MmO0P4zzZiidzse-oiPx_fRMixajY56Y/view?usp=drivesdk"}, {"ftype": "pdf", "fsize": "376.393KB", "year": "2022", "revoked": false, "url": "https://drive.google.com/file/d/1v7_q66Oue7j2QHHfByvoLoOrT2Gqi3QL/view?usp=drivesdk"}, {"ftype": "pdf", "fsize": "378.914KB", "year": "2023", "revoked": false, "url": "https://drive.google.com/file/d/1OEHtbME6WZ8QYvZwVKV9mu8Huyrsjql4/view?usp=drivesdk"}, {"ftype": "pdf", "fsize": "364.0KB", "year": "2024", "revoked": false, "url": "https://drive.google.com/file/d/1u5TbX6MdoHfyI04hoOEiE4otywbEJRSy/view?usp=drivesdk"}, {"ftype": "pdf", "fsize": "610.983KB", "year": "2025", "revoked": false, "url": "https://drive.google.com/file/d/1AJDqRbj1IgihgrdpePvjD-mFkjBCZd4O/view?usp=drivesdk"}]}, {"type": "cms", "files": [{"ftype": "pdf", "fsize": "684.708KB", "year": "2023-2025", "revoked": false, "url": "https://drive.google.com/file/d/1NN1pBBkdY_OIi3dmA08j_F1tAGYm-5AC/view?usp=drivesdk"}, {"ftype": "pdf", "fsize": "355.553KB", "year": "2026-2028", "revoked": false, "url": "https://drive.google.com/file/d/1lv9NQNDJJ-LQcDXlKEMFB_aJcfA6qe8X/view?usp=drivesdk"}]}, {"type": "lcr", "files": [{"ftype": "pdf", "fsize": "255.877KB", "year": 2023, "revoked": false, "url": "https://drive.google.com/file/d/107HV_t0u9j3r7rw6dGyjSZBUtCR7lujN/view?usp=drivesdk"}]}, {"type": "sli", "files": [{"ftype": "pdf", "fsize": "0.764KB", "year": 2025, "revoked": false, "url": "https://drive.google.com/file/d/1XGf9U95IlA2xsu7baHzha1-29cud3nDt/view?usp=drivesdk"}]}]}