{"pws": {"id": 2286027, "name": "10.0 Academy / Gymnastics", "class": "NC", "town": "Stow", "winter": 30, "summer": 60, "connections": 1, "mone": "650 Great Road", "mtwo": "", "mtown": "Littleton", "mstate": "MA", "mzip": "01460"}, "documents": [{"type": "cert", "ftype": "pdf", "fsize": "91.909KB", "year": "2025", "revoked": false, "url": "https://drive.google.com/file/d/1ABBVwp12ZvYW3QGojZOCwkcG-dpDGTBs/view?usp=drivesdk"}, {"type": "ccr", "ftype": "pdf", "fsize": "382.113KB", "year": "2025", "revoked": false, "url": "https://drive.google.com/file/d/1_tYcWkwCzv6ytmwaW-hFeO-d2hOQsAJH/view?usp=drivesdk"}, {"type": "cms", "ftype": "pdf", "fsize": "338.606KB", "year": "2023-2025", "revoked": false, "url": "https://drive.google.com/file/d/1DtUoedGHwKzbweLz2bThdeWHBLs7VXM6/view?usp=drivesdk"}]}