{"pws": {"id": 2286005, "name": "Hale Middle School", "class": "NTNC", "town": "Stow", "winter": 321, "summer": 25, "connections": 1, "mone": "50 Mechanic Street", "mtwo": "", "mtown": "Bolton", "mstate": "MA", "mzip": "01740", "status": "ACTIVE"}, "documents": [{"type": "asr", "files": []}, {"type": "ccr", "files": []}, {"type": "cert", "files": [{"ftype": "pdf", "fsize": "107.623KB", "year": "2015", "revoked": false, "url": "https://drive.google.com/file/d/1Y134g0MAkdvf8mgYaO52smYt_Ad-DEss/view?usp=drivesdk"}, {"ftype": "pdf", "fsize": "107.348KB", "year": "2016", "revoked": false, "url": "https://drive.google.com/file/d/1zUSBm_OLawUd9fn9hlg_ZLrx5eCZiBO3/view?usp=drivesdk"}, {"ftype": "pdf", "fsize": "95.561KB", "year": "2017", "revoked": false, "url": "https://drive.google.com/file/d/1dLUmU3Lby6JE6w-hGm_bIc5vIXA9g_vB/view?usp=drivesdk"}, {"ftype": "pdf", "fsize": "96.258KB", "year": "2018", "revoked": false, "url": "https://drive.google.com/file/d/1vLSzSRLZuMPu0wwMfNy2JTiIlZImIFHG/view?usp=drivesdk"}, {"ftype": "pdf", "fsize": "96.272KB", "year": "2019", "revoked": false, "url": "https://drive.google.com/file/d/1R61M_bMW25yLTvJ2DK_h9HRxc34qq7ho/view?usp=drivesdk"}, {"ftype": "pdf", "fsize": "95.829KB", "year": "2020", "revoked": false, "url": "https://drive.google.com/file/d/1miO-y3zmuZG7FaEDOM1fvpRlRco2WtzT/view?usp=drivesdk"}, {"ftype": "pdf", "fsize": "90.714KB", "year": "2021", "revoked": false, "url": "https://drive.google.com/file/d/1laQHmC34_h5Jybs5WjQtL8EY46hI7M3x/view?usp=drivesdk"}, {"ftype": "pdf", "fsize": "90.22KB", "year": "2022", "revoked": false, "url": "https://drive.google.com/file/d/1gg_y-2-WZSvY9xXMSQxhmmrn_APtruOV/view?usp=drivesdk"}, {"ftype": "pdf", "fsize": "89.42KB", "year": "2023", "revoked": false, "url": "https://drive.google.com/file/d/1XhkpAXUh12Nm6X7oV0LnRQwnwyvjeZsg/view?usp=drivesdk"}, {"ftype": "pdf", "fsize": "91.392KB", "year": "2024", "revoked": false, "url": "https://drive.google.com/file/d/1qroGNUDToGVcE1mEZ7REHaQj2OWZtjHH/view?usp=drivesdk"}, {"ftype": "pdf", "fsize": "91.434KB", "year": "2025", "revoked": false, "url": "https://drive.google.com/file/d/10CODTBd20hxvWy0JlQEF6JXCBqWQocmw/view?usp=drivesdk"}, {"ftype": "pdf", "fsize": "60.287KB", "year": "2026", "revoked": false, "url": "https://drive.google.com/file/d/1GPn-LNEK-mAUk2bPQfqjRy9ki5CX7Y3C/view?usp=drivesdk"}]}, {"type": "wqr", "files": [{"ftype": "pdf", "fsize": "99.777KB", "year": "2015", "revoked": false, "url": "https://drive.google.com/file/d/1vdpSmYFgUoQ5n8v0F1K08YKsgWyifj_h/view?usp=drivesdk"}, {"ftype": "pdf", "fsize": "149.331KB", "year": "2016", "revoked": false, "url": "https://drive.google.com/file/d/1ywDd-W_7g2AKAGmJWe7X4t_ETWzab_p4/view?usp=drivesdk"}, {"ftype": "pdf", "fsize": "229.634KB", "year": "2017", "revoked": false, "url": "https://drive.google.com/file/d/1Wyi89sLd9GGtYL4e7Xl2xBe8kwIJ0XSX/view?usp=drivesdk"}, {"ftype": "pdf", "fsize": "199.375KB", "year": "2018", "revoked": false, "url": "https://drive.google.com/file/d/198OQHirapAMSagi2IhHTQHDkOlNexM-E/view?usp=drivesdk"}, {"ftype": "pdf", "fsize": "204.654KB", "year": "2019", "revoked": false, "url": "https://drive.google.com/file/d/1uQTudc2ItLYelg7CeyWTBxISoKlceUqc/view?usp=drivesdk"}, {"ftype": "pdf", "fsize": "229.159KB", "year": "2020", "revoked": false, "url": "https://drive.google.com/file/d/1wNpGJIPjHrteKo9w-Sbjy-0VLZ1SbaZp/view?usp=drivesdk"}, {"ftype": "pdf", "fsize": "294.282KB", "year": "2021", "revoked": false, "url": "https://drive.google.com/file/d/1M6c5_iC02bBX71oHwCfxxWqmBNyT3FP3/view?usp=drivesdk"}, {"ftype": "pdf", "fsize": "374.478KB", "year": "2022", "revoked": false, "url": "https://drive.google.com/file/d/1b2Jpk0LczLB9AghsWNFwAIeoVJHTEYG7/view?usp=drivesdk"}, {"ftype": "pdf", "fsize": "374.703KB", "year": "2023", "revoked": false, "url": "https://drive.google.com/file/d/1ksWUURcQl3LnQgJvNDHLZnqU8mJjJ7ID/view?usp=drivesdk"}, {"ftype": "pdf", "fsize": "361.707KB", "year": "2024", "revoked": false, "url": "https://drive.google.com/file/d/1DpXhr1XyuZO7BygG0FGQfenhTIIx1Oef/view?usp=drivesdk"}, {"ftype": "pdf", "fsize": "604.072KB", "year": "2025", "revoked": false, "url": "https://drive.google.com/file/d/1rIZd440UPXHYKAhgSJKeyZpMBE8S4r20/view?usp=drivesdk"}]}, {"type": "cms", "files": [{"ftype": "pdf", "fsize": "357.58KB", "year": "2023-2025", "revoked": false, "url": "https://drive.google.com/file/d/1dFY_mkvhEbkBsWJUVV8t4wg3g8fWJED1/view?usp=drivesdk"}, {"ftype": "pdf", "fsize": "370.451KB", "year": "2026-2028", "revoked": false, "url": "https://drive.google.com/file/d/1PEtdUnBlifJ0SZpPCVJahNrFJWay1hv5/view?usp=drivesdk"}]}, {"type": "lcr", "files": [{"ftype": "pdf", "fsize": "254.96KB", "year": 2023, "revoked": false, "url": "https://drive.google.com/file/d/1IXILnYfMvG7wLZBkGFbnDofxwPwPgaIX/view?usp=drivesdk"}]}, {"type": "sli", "files": [{"ftype": "pdf", "fsize": "0.74KB", "year": 2025, "revoked": false, "url": "https://drive.google.com/file/d/12rVY32WV8EbBqZe06XzQZiDP0x6-tFEi/view?usp=drivesdk"}]}]}