{"pws": {"id": 3301030, "name": "Business Park West Condominium Trust", "class": "NTNC", "town": "Tyngsborough", "winter": 30, "summer": 30, "connections": 1, "mone": "500 Business Park Dr", "mtwo": "", "mtown": "Tyngsborough", "mstate": "MA", "mzip": "01879"}, "documents": [{"type": "cert", "ftype": "pdf", "fsize": "91.601KB", "year": "2024", "revoked": false, "url": "https://drive.google.com/file/d/1tnESHaY-nr8B2Bb1zE-iDyS0lEPmPIAr/view?usp=drivesdk"}, {"type": "ccr", "ftype": "pdf", "fsize": "375.939KB", "year": "2023", "revoked": false, "url": "https://drive.google.com/file/d/1wwpBfumEi0oHH6NgI-G5IIXOdPJNgLeI/view?usp=drivesdk"}, {"type": "cms", "ftype": "pdf", "fsize": "331.99KB", "year": "2023-2025", "revoked": false, "url": "https://drive.google.com/file/d/1-byLod5_2Y6mR1Nd4SgeY2gShjdd4yXm/view?usp=drivesdk"}, {"type": "lcr", "ftype": "pdf", "fsize": "209.95KB", "year": "", "revoked": false, "url": "https://drive.google.com/file/d/1B9E08xu-D7Q_uQsmxDXuJsZU6NXeVFi6/view?usp=drivesdk"}]}