{"documents": [{"revoked": false, "url": "https://drive.google.com/file/d/10A5ltzndHXwLNGzhEmnrS7n-_JbWrLEe/view?usp=drivesdk", "fsize": "96KB", "ftype": "pdf", "year": "2018", "type": "cert"}, {"revoked": false, "url": "https://drive.google.com/file/d/1sP0GzoN7sktPIDMp5tqUjkMs-20Cvy_6/view?usp=drivesdk", "fsize": "264KB", "ftype": "pdf", "year": "2017", "type": "ccr"}, {"revoked": false, "url": "https://drive.google.com/file/d/1ISE4LimpWtZStaT9fSlgCByDVGIg86iJ/view?usp=drivesdk", "fsize": "5KB", "ftype": "pdf", "year": "2017-2019", "type": "cms"}], "pws": {"town": "Attleboro", "summer": 25, "mone": "P.O. Box 328", "winter": 25, "mtwo": "", "mzip": "02375", "id": 4016001, "connections": 1, "mtown": "South Easton", "class": "NC", "mstate": "MA", "name": "Simpson Spring (Attleboro) Vend"}}