{"documents": [{"revoked": false, "url": "https://drive.google.com/file/d/1MyVr1nkeCtmi0q6sTr5K-PXjkpTB0xy2/view?usp=drivesdk", "fsize": "95KB", "ftype": "pdf", "year": "2020", "type": "cert"}, {"revoked": false, "url": "https://drive.google.com/file/d/1IesZIQWuyuJGd7H_Bpwm01ZnIt4jNBzy/view?usp=drivesdk", "fsize": "137KB", "ftype": "pdf", "year": "2019", "type": "ccr"}, {"revoked": false, "url": "https://drive.google.com/file/d/1_at1AhJnUIlmzXTD7dvBnhBZh56NDqQL/view?usp=drivesdk", "fsize": "11KB", "ftype": "pdf", "year": "2020-2022", "type": "cms"}], "pws": {"town": "Brockton", "summer": 40, "mone": "P.O. Box 328", "winter": 40, "mtwo": "", "mzip": "02375", "id": 4044007, "connections": 1, "mtown": "South Easton", "class": "NC", "mstate": "MA", "name": "Simpson Spring (Brockton) Vend"}}