{"pws": {"id": 4044000, "name": "Brockton Water Department", "class": "COM", "town": "Brockton", "winter": 93810, "summer": 93810, "connections": 24660, "mone": "45 School St", "mtwo": "City Hall 3Rd Floor Dpw Office", "mtown": "Brockton", "mstate": "MA", "mzip": "02301"}, "documents": [{"type": "cert", "ftype": "pdf", "fsize": "95.046KB", "year": "2020", "revoked": false, "url": "https://drive.google.com/file/d/1Wqa1nUL5QzjwBtLZWo6I7DEZpgSIqQyf/view?usp=drivesdk"}, {"type": "cms", "ftype": "pdf", "fsize": "59.634KB", "year": "2020-2022", "revoked": false, "url": "https://drive.google.com/file/d/1mff2A79vEiOJyRsa9moXfJDL6astlhyf/view?usp=drivesdk"}, {"type": "lcr", "ftype": "pdf", "fsize": "262.229KB", "year": "", "revoked": false, "url": "https://drive.google.com/file/d/1GEJF39uqdaYEdNoCmT-KZm7Dy3Lpz1jp/view?usp=drivesdk"}]}