{"documents": [{"revoked": false, "url": "https://drive.google.com/file/d/1Wkr5aCVMVXShwisJtXdNxUlWbE28rO5I/view?usp=drivesdk", "fsize": "96KB", "ftype": "pdf", "year": "2019", "type": "cert"}, {"revoked": false, "url": "https://drive.google.com/file/d/1a3iAuL0YQJVG3VpqtMdy6agO74sENJ9O/view?usp=drivesdk", "fsize": "136KB", "ftype": "pdf", "year": "2019", "type": "ccr"}, {"revoked": false, "url": "https://drive.google.com/file/d/1LMAFzcxY4cfMOpf_T9aj4mA2R3TiN0rc/view?usp=drivesdk", "fsize": "8KB", "ftype": "pdf", "year": "2017-2019", "type": "cms"}], "pws": {"town": "Chatham", "summer": 130, "mone": "Box 772", "winter": 130, "mtwo": "", "mzip": "02633", "id": 4055005, "connections": 1, "mtown": "Chatham", "class": "NC", "mstate": "MA", "name": "Pleasant Bay Village Motel"}}