{"pws": {"id": 4062002, "name": "Chilmark Tavern", "class": "NC", "town": "Chilmark", "winter": 0, "summer": 99, "connections": 2, "mone": "377 South Road", "mtwo": "", "mtown": "Chilmark", "mstate": "MA", "mzip": "02535"}, "documents": [{"type": "cert", "ftype": "pdf", "fsize": "91.325KB", "year": "2025", "revoked": false, "url": "https://drive.google.com/file/d/1lWvUYBAm42eNxiTtsG9kyRuFSRbGZOQ8/view?usp=drivesdk"}, {"type": "ccr", "ftype": "pdf", "fsize": "197.008KB", "year": "2025", "revoked": false}, {"type": "cms", "ftype": "pdf", "fsize": "341.313KB", "year": "2023-2025", "revoked": false, "url": "https://drive.google.com/file/d/1E4ip4DJvJQ4JPFmpU_ht7J6Mz_I7UN1D/view?usp=drivesdk"}, {"type": "cms", "ftype": "pdf", "fsize": "111.748KB", "year": "2026-2028", "revoked": false, "url": "https://drive.google.com/file/d/1FvxvPyKHSwlgv2vaDsMpA7VY95U5OiSf/view?usp=drivesdk"}]}