{"documents": [{"revoked": false, "url": "https://drive.google.com/file/d/1MDudTq6MB2vEJ40QXDoS2lZseAGURiYv/view?usp=drivesdk", "fsize": "96KB", "ftype": "pdf", "year": "2019", "type": "cert"}, {"revoked": false, "url": "https://drive.google.com/file/d/12F-8VJWSaRDbZhGkyYKMS4z5gNvyGXvV/view?usp=drivesdk", "fsize": "135KB", "ftype": "pdf", "year": "2018", "type": "ccr"}, {"revoked": false, "url": "https://drive.google.com/file/d/1vVB3fv36LGaSMzmQAGt-V0Z9yl3ZJfUr/view?usp=drivesdk", "fsize": "7KB", "ftype": "pdf", "year": "2017-2019", "type": "cms"}], "pws": {"town": "Eastham", "summer": 28, "mone": "The Waterguy", "winter": 18, "mtwo": "38 Ruby St", "mzip": "02673", "id": 4086036, "connections": 1, "mtown": "West Yarmouth", "class": "NC", "mstate": "MA", "name": "Village Green Shopping Center"}}