{"pws": {"id": 4086046, "name": "Captains Quarters Motel And Conf. Ctr.", "class": "NC", "town": "Eastham", "winter": 0, "summer": 101, "connections": 2, "mone": "C/O Sanat Tankalwala", "mtwo": "P.O. Box 1896", "mtown": "North Eastham", "mstate": "MA", "mzip": "02651"}, "documents": [{"type": "cert", "ftype": "pdf", "fsize": "91.439KB", "year": "2024", "revoked": false, "url": "https://drive.google.com/file/d/17pYVuCy_V4xqKab8yBI0aC226EyquGlf/view?usp=drivesdk"}, {"type": "ccr", "ftype": "pdf", "fsize": "369.279KB", "year": "2023", "revoked": false, "url": "https://drive.google.com/file/d/1tc1RW17BCEBuPcXCcaGjgIqnRBcul1aB/view?usp=drivesdk"}, {"type": "cms", "ftype": "pdf", "fsize": "345.18KB", "year": "2023-2025", "revoked": false, "url": "https://drive.google.com/file/d/14D9EvnhIQhIKKkuSbi_eRMR8GqRjPwP2/view?usp=drivesdk"}]}