{"pws": {"id": 4293007, "name": "Simpson Spring (Taunton) Vend", "class": "NC", "town": "Taunton", "winter": 25, "summer": 25, "connections": 1, "mone": "P.O. Box 328", "mtwo": "", "mtown": "South Easton", "mstate": "MA", "mzip": "02375", "status": "DECLASSIFIED"}, "documents": [{"type": "asr", "files": []}, {"type": "ccr", "files": []}, {"type": "cert", "files": [{"ftype": "pdf", "fsize": "108.343KB", "year": "2015", "revoked": false, "url": "https://drive.google.com/file/d/11KZG_x6yRJKqUvKJ35SR0upt2sepXIkb/view?usp=drivesdk"}, {"ftype": "pdf", "fsize": "108.064KB", "year": "2016", "revoked": false, "url": "https://drive.google.com/file/d/1EhWXf09irU1JOKReuwt1KEGc2vHfqpky/view?usp=drivesdk"}, {"ftype": "pdf", "fsize": "96.272KB", "year": "2017", "revoked": false, "url": "https://drive.google.com/file/d/1XOabo9CyBCkM9F3N4of5jlJnKpG3bpea/view?usp=drivesdk"}, {"ftype": "pdf", "fsize": "96.971KB", "year": "2018", "revoked": false, "url": "https://drive.google.com/file/d/1ypKLaDjdnftHtQOjqMSlsD9aDzqG-Zv-/view?usp=drivesdk"}, {"ftype": "pdf", "fsize": "96.873KB", "year": "2019", "revoked": false, "url": "https://drive.google.com/file/d/1U2ZIJQt5LmcJqwppgxeeV5mrkF4shUQN/view?usp=drivesdk"}, {"ftype": "pdf", "fsize": "96.544KB", "year": "2020", "revoked": false, "url": "https://drive.google.com/file/d/1-g4REUqKW8WF6hImZtCkCEIYEmI184QK/view?usp=drivesdk"}, {"ftype": "pdf", "fsize": "91.342KB", "year": "2021", "revoked": false, "url": "https://drive.google.com/file/d/11QNe0Hckm5rb1ulSoIpPjf7ByhZo916X/view?usp=drivesdk"}, {"ftype": "pdf", "fsize": "90.841KB", "year": "2022", "revoked": false, "url": "https://drive.google.com/file/d/1yab9Fzuo6fDm_Ae590JvnfHGNr_A7Pdq/view?usp=drivesdk"}, {"ftype": "pdf", "fsize": "90.043KB", "year": "2023", "revoked": false, "url": "https://drive.google.com/file/d/1VhOwnq7e9io60WuAV5ef_oQlbe3M4GYU/view?usp=drivesdk"}]}, {"type": "wqr", "files": [{"ftype": "pdf", "fsize": "117.434KB", "year": "2015", "revoked": false, "url": "https://drive.google.com/file/d/1SEqz2kyjiCRYkISLsn40-Ah-gfN56qWw/view?usp=drivesdk"}, {"ftype": "pdf", "fsize": "264.53KB", "year": "2016", "revoked": false, "url": "https://drive.google.com/file/d/1K_fnuhiwS6yPjrkZDKTAnOEk7mtOnl-9/view?usp=drivesdk"}, {"ftype": "pdf", "fsize": "265.184KB", "year": "2017", "revoked": false, "url": "https://drive.google.com/file/d/18_rDfq1xdLlIJyYuafXRNyvWiULkb-ii/view?usp=drivesdk"}, {"ftype": "pdf", "fsize": "262.972KB", "year": "2018", "revoked": false, "url": "https://drive.google.com/file/d/1oVsILzp6Av3SDVih0XeBlNoesbBsRdb4/view?usp=drivesdk"}, {"ftype": "pdf", "fsize": "136.346KB", "year": "2019", "revoked": false, "url": "https://drive.google.com/file/d/1CeWswel9GycSokfsrwb65u_8MZof7mDz/view?usp=drivesdk"}, {"ftype": "pdf", "fsize": "116.545KB", "year": "2020", "revoked": false, "url": "https://drive.google.com/file/d/1F04ikA6US0XHPjI9yJiqRMGq_yZWEFuh/view?usp=drivesdk"}, {"ftype": "pdf", "fsize": "118.153KB", "year": "2021", "revoked": false, "url": "https://drive.google.com/file/d/1pY7_ViG6lTD5W4DCqU8Bn4Yx8Zy8Bwhx/view?usp=drivesdk"}, {"ftype": "pdf", "fsize": "223.346KB", "year": "2022", "revoked": false, "url": "https://drive.google.com/file/d/1EBnJ-qzKIgxg2w79995NguGnhOh-i--N/view?usp=drivesdk"}]}, {"type": "cms", "files": [{"ftype": "pdf", "fsize": "246.453KB", "year": "2023-2025", "revoked": false, "url": "https://drive.google.com/file/d/1H4PLMlFTt_-uWqVem3vSDpc-x4qoXyph/view?usp=drivesdk"}]}, {"type": "lcr", "files": []}, {"type": "sli", "files": []}]}