{"pws": {"id": 4334031, "name": "Dcr Horseneck Beach State Reservation", "class": "NC", "town": "Westport", "winter": 2, "summer": 3000, "connections": 5, "mone": "251 Causway Street, 9Th Floor", "mtwo": "Attn; Susan Hamilton", "mtown": "Boston", "mstate": "MA", "mzip": "02114"}, "documents": [{"type": "cert", "ftype": "pdf", "fsize": "95.874KB", "year": "2020", "revoked": false, "url": "https://drive.google.com/file/d/19q-NcyHxQ11T6ByBuxQBozvLAdVAW_Et/view?usp=drivesdk"}, {"type": "ccr", "ftype": "pdf", "fsize": "118.305KB", "year": "2020", "revoked": false, "url": "https://drive.google.com/file/d/186CtAB0SfSF9EmWYPILV1memigKMFlMl/view?usp=drivesdk"}, {"type": "cms", "ftype": "pdf", "fsize": "24.691KB", "year": "2020-2022", "revoked": false, "url": "https://drive.google.com/file/d/1bfFn8P5pmCvGJ11Ny5pVYBAfRwWjeVNH/view?usp=drivesdk"}]}