{"pws": {"id": 4334024, "name": "Ten Cousins", "class": "NC", "town": "Westport", "winter": 150, "summer": 150, "connections": 1, "mone": "P O Box 248", "mtwo": "", "mtown": "Westport", "mstate": "MA", "mzip": "02790"}, "documents": [{"type": "cert", "ftype": "pdf", "fsize": "90.995KB", "year": "2025", "revoked": false, "url": "https://drive.google.com/file/d/1eDOiIemU8XjFUdrvXJRqA0k7wFs78mf-/view?usp=drivesdk"}, {"type": "ccr", "ftype": "pdf", "fsize": "196.449KB", "year": "2025", "revoked": false, "url": "https://drive.google.com/file/d/1i6LttGTQFZYptzs9a3kycWIk74cas66r/view?usp=drivesdk"}, {"type": "cms", "ftype": "pdf", "fsize": "338.392KB", "year": "2023-2025", "revoked": false, "url": "https://drive.google.com/file/d/1L1tTbPcqrKlnrnIQtK6nWMeTDufZ1fAR/view?usp=drivesdk"}, {"type": "cms", "ftype": "pdf", "fsize": "110.103KB", "year": "2026-2028", "revoked": false, "url": "https://drive.google.com/file/d/1kh95YWhwNqAabw09lB1mumPQsiqCpcNX/view?usp=drivesdk"}]}