{"pws": {"id": 4334075, "name": "Westport Legion Llc", "class": "NTNC", "town": "Westport", "winter": 25, "summer": 25, "connections": 1, "mone": "P O Box 2516", "mtwo": "", "mtown": "Fall River", "mstate": "MA", "mzip": "02722"}, "documents": [{"type": "cert", "ftype": "pdf", "fsize": "91.372KB", "year": "2025", "revoked": false, "url": "https://drive.google.com/file/d/1Qy3HuZQCGruItN9UNUebE6xzPIiVGLfv/view?usp=drivesdk"}, {"type": "ccr", "ftype": "pdf", "fsize": "605.818KB", "year": "2025", "revoked": false, "url": "https://drive.google.com/file/d/1e_2XmuO8GDmgpJZfm4xMscu0g3twiucS/view?usp=drivesdk"}, {"type": "cms", "ftype": "pdf", "fsize": "355.369KB", "year": "2023-2025", "revoked": false, "url": "https://drive.google.com/file/d/19hfg4NQSyyXNxw6KLOizWdRZCGE2HTe7/view?usp=drivesdk"}, {"type": "lcr", "ftype": "pdf", "fsize": "249.139KB", "year": "", "revoked": false, "url": "https://drive.google.com/file/d/1l2TWXGl3HwtCvAMkstB7WCrzVnEnDiqz/view?usp=drivesdk"}, {"type": "sli", "ftype": "csv", "fsize": "0.869KB", "year": "2024", "revoked": false, "url": "https://drive.google.com/file/d/1_-8mB9r_X7yK54JkMPLW7ZhkkszpY4Xa/view?usp=drivesdk"}]}