{"pws": {"id": 4334076, "name": "Westport Yacht Club Inc.", "class": "NC", "town": "Westport", "winter": 0, "summer": 100, "connections": 1, "mone": "P.O. Box 3689", "mtwo": "", "mtown": "Westport", "mstate": "MA", "mzip": "02790"}, "documents": [{"type": "cert", "ftype": "pdf", "fsize": "96.551KB", "year": "2020", "revoked": false, "url": "https://drive.google.com/file/d/1yKMhPiPzPRsxsVVLwZih89Rby6AM3RI_/view?usp=drivesdk"}, {"type": "ccr", "ftype": "pdf", "fsize": "136.461KB", "year": "2019", "revoked": false, "url": "https://drive.google.com/file/d/1zjhKpr7Hh_5BFccVxXBEPnOCJhltJF0Z/view?usp=drivesdk"}, {"type": "cms", "ftype": "pdf", "fsize": "15.518KB", "year": "2020-2022", "revoked": false, "url": "https://drive.google.com/file/d/1VA8hcLoCbY-BvL-7ypKWn2r4x97bAGua/view?usp=drivesdk"}]}